{"killedby":"死於","player":"玩家頭顱","allay":"悅靈頭顱","axolotl":{"blue":"藍色六角恐龍頭顱","cyan":"青色六角恐龍頭顱","gold":"金色角恐龍頭顱","lucy":"粉紅色六角恐龍頭顱","wild":"棕色六角恐龍頭顱"},"bat":"蝙蝠頭顱","bee":{"angry_pollinated":"憤怒授粉的蜜蜂頭顱","angry":"憤怒蜜蜂頭顱","pollinated":"授粉的蜜蜂頭顱","none":"蜜蜂頭顱"},"blaze":"烈焰人頭顱","camel":"駱駝頭顱","cat":{"all_black":"黑貓頭顱","black":"燕尾服貓頭顱","british_shorthair":"英國短毛貓貓頭顱","calico":"花貓布貓頭顱","jellie":"灰橘虎斑貓頭顱","persian":"波斯貓頭顱","ragdoll":"布偶貓頭顱","red":"橘虎斑貓頭顱","siamese":"暹羅貓頭顱","tabby":"虎斑貓頭顱","white":"白色貓頭顱","wild_ocelot":"豹貓頭顱"},"cave_spider":"洞穴蜘蛛頭顱","chicken":"雞頭顱","cod":"鱈魚頭顱","cow":"牛頭顱","creeper":"苦力怕頭顱","creepeer_charged":"帶電的苦力怕頭顱","dolphin":"海豚頭顱","donkey":"驢頭顱","drowned":"沉屍頭顱","elder_guardian":"遠古守衛者頭顱","ender_dragon":"終界龍頭顱","enderman":"終界使者頭顱","endermite":"終界蟎頭顱","evoker":"喚魔者頭顱","fox":{"red":"赤狐狸頭顱","snow":"雪狐狸頭顱"},"frog":{"cold":"寒帶青蛙頭顱","temperate":"溫帶青蛙頭顱","warm":"熱帶青蛙頭顱"},"ghast":"地獄幽靈頭顱","giant":"巨人頭顱","glow_squid":"螢光魷魚頭顱","goat":{"normal":"山羊頭顱","screaming":"尖叫山羊頭顱"},"guardian":"守衛者頭顱","hoglin":"豬布獸頭顱","horse":{"black":"黑色馬頭顱","brown":"棕色馬頭顱","chestnut":"栗子色馬頭顱","creamy":"奶油色馬頭顱","dark_brown":"深棕色馬頭顱","gray":"灰色馬頭顱","white":"白色馬頭顱"},"husk":"屍殼頭顱","illusioner":"幻術師頭顱","iron_golem":"鐵傀儡頭顱","llama":{"brown":"棕色羊駝頭顱","creamy":"奶油色羊駝頭顱","gray":"灰色羊駝頭顱","white":"白色羊駝頭顱"},"magma_cube":"岩漿立方怪頭顱","mule":"馬騾頭顱","mushroom_cow":{"red":"蘑菇牛頭顱","brown":"棕色蘑菇牛頭顱"},"panda":{"aggressive":"好鬥熊貓頭顱","brown":"棕色熊貓頭顱","lazy":"懶惰熊貓頭顱","normal":"熊貓頭顱","playful":"愛玩的熊貓頭顱","weak":"虛弱熊貓頭顱","worried":"擔心熊貓頭顱"},"parrot":{"blue":"藍色鸚鵡頭顱","cyan":"青色鸚鵡頭顱","gray":"灰色鸚鵡頭顱","green":"綠色鸚鵡頭顱","red":"紅色鸚鵡頭顱"},"phantom":"夜魅頭顱","pig":"豬頭顱","piglin":"豬布林頭顱","piglin_brute":"豬布林蠻兵頭顱","pig_zombie":"殭屍化豬布林頭顱","pillager":"掠奪者頭顱","polar_bear":"北極熊頭顱","pufferfish":"河豚魚頭顱","rabbit":{"black":"黑色兔子頭顱","black_and_white":"黑白斑點兔子頭顱","brown":"棕色兔子頭顱","gold":"奶油色兔子頭顱","salt_and_pepper":"胡椒色兔子頭顱","the_killer_bunny":"殺手兔子頭顱","toast":"Toast兔子頭顱","white":"白色兔子頭顱"},"ravager":"劫毀獸頭顱","salmon":"鮭魚頭顱","sheep":{"black":"黑色羊頭顱","blue":"藍色羊頭顱","brown":"棕色羊頭顱","cyan":"青色羊頭顱","gray":"灰色羊頭顱","green":"綠色羊頭顱","jeb_":"Jeb_羊頭顱","light_blue":"淺藍羊頭顱","light_gray":"淺灰色羊頭顱","lime":"淺綠色羊頭顱","magenta":"洋紅羊頭顱","orange":"橘色羊頭顱","pink":"粉紅羊頭顱","purple":"紫色羊頭顱","red":"紅色羊頭顱","white":"白色羊頭顱","yellow":"黃色羊頭顱"},"shulker":"界伏蚌頭顱","silverfish":"蠹魚頭顱","skeleton":"骷髏頭顱","skeleton_horse":"骷髏馬頭顱","slime":"史萊姆頭顱","sniffer":"嗅探獸的頭顱","snowman":"雪人頭顱","spider":"蜘蛛頭顱","squid":"烏賊頭顱","stray":"流髑頭顱","strider":"熾足獸頭顱","strider_shivering":"發抖的熾足獸頭顱","tadpole":"蝌蚪頭顱","trader_llama":{"brown":"棕色羊駝商人頭顱","creamy":"奶油色羊駝商人頭顱","gray":"灰色羊駝商人頭顱","white":"白色羊駝商人頭顱"},"tropical_fish":{"tropical_fish":"熱帶魚頭顱","anemone":"海葵魚頭顱","black_tang":"長鼻高鰭刺尾魚頭顱","blue_tang":"擬刺尾鯛頭顱","butterflyfish":"蝴蝶魚頭顱","cichlid":"慈鯛頭顱","clownfish":"小丑魚頭顱","cotton_candy_betta":"五彩搏魚頭顱","dottyback":"紅黃繡雀鯛頭顱","emperor_red_snapper":"川紋笛鯛頭顱","goatfish":"鬚鯛頭顱","moorish_idol":"角蝶魚頭顱","ornate_butterflyfish":"華麗蝴蝶魚頭顱","parrotfish":"鸚哥魚頭顱","queen_angelfish":"額斑刺蝶魚頭顱","red_cichlid":"赤慈鯛頭顱","red_lipped_blenny":"紅唇真蛇䲁頭顱","red_snapper":"西大西洋笛鯛頭顱","threadfin":"馬鮁頭顱","tomato_clownfish":"白條雙鋸魚頭顱","triggerfish":"鱗魨頭顱","yellow_parrotfish":"高鰭鸚哥魚頭顱","yellow_tang":"黃高鰭刺尾魚頭顱"},"turtle":"海龜頭顱","vex":"惱鬼頭顱","villager":{"desert":{"armorer":"沙漠盔甲匠村民頭顱","butcher":"沙漠屠夫村民頭顱","cartographer":"沙漠製圖師村民頭顱","cleric":"沙漠神職人員村民頭顱","farmer":"沙漠農夫村民頭顱","fisherman":"沙漠漁夫村民頭顱","fletcher":"沙漠製箭師村民頭顱","leatherworker":"沙漠皮匠村民頭顱","librarian":"沙漠圖書管理員村民頭顱","mason":"沙漠石匠村民頭顱","nitwit":"沙漠傻子村民頭顱","none":"沙漠村民頭顱","shepherd":"沙漠牧羊人村民頭顱","toolsmith":"沙漠工具匠村民頭顱","weaponsmith":"沙漠武器匠村民頭顱"},"jungle":{"armorer":"叢林盔甲匠村民頭顱","butcher":"叢林屠夫村民頭顱","cartographer":"叢林製圖師村民頭顱","cleric":"叢林神職人員村民頭顱","farmer":"叢林農夫村民頭顱","fisherman":"叢林漁夫村民頭顱","fletcher":"叢林製箭師村民頭顱","leatherworker":"叢林皮匠村民頭顱","librarian":"叢林圖書管理員村民頭顱","mason":"叢林石匠村民頭顱","nitwit":"叢林傻子村民頭顱","none":"叢林村民頭顱","shepherd":"叢林牧羊人村民頭顱","toolsmith":"叢林工具匠村民頭顱","weaponsmith":"叢林武器匠村民頭顱"},"plains":{"armorer":"平原盔甲匠村民頭顱","butcher":"平原屠夫村民頭顱","cartographer":"平原製圖師村民頭顱","cleric":"平原神職人員村民頭顱","farmer":"平原農夫村民頭顱","fisherman":"平原漁夫村民頭顱","fletcher":"平原製箭師村民頭顱","leatherworker":"平原皮匠村民頭顱","librarian":"平原圖書管理員村民頭顱","mason":"平原石匠村民頭顱","nitwit":"平原傻子村民頭顱","none":"平原村民頭顱","shepherd":"平原牧羊人村民頭顱","toolsmith":"平原工具匠村民頭顱","weaponsmith":"平原武器匠村民頭顱"},"savanna":{"armorer":"莽原盔甲匠村民頭顱","butcher":"莽原屠夫村民頭顱","cartographer":"莽原製圖師村民頭顱","cleric":"莽原神職人員村民頭顱","farmer":"莽原農夫村民頭顱","fisherman":"莽原漁夫村民頭顱","fletcher":"莽原製箭師村民頭顱","leatherworker":"莽原皮匠村民頭顱","librarian":"莽原圖書管理員村民頭顱","mason":"莽原石匠村民頭顱","nitwit":"莽原傻子村民頭顱","none":"莽原村民頭顱","shepherd":"莽原牧羊人村民頭顱","toolsmith":"莽原工具匠村民頭顱","weaponsmith":"莽原武器匠村民頭顱"},"snow":{"armorer":"雪原盔甲匠村民頭顱","butcher":"雪原屠夫村民頭顱","cartographer":"雪原製圖師村民頭顱","cleric":"雪原神職人員村民頭顱","farmer":"雪原農夫村民頭顱","fisherman":"雪原漁夫村民頭顱","fletcher":"雪原製箭師村民頭顱","leatherworker":"雪原皮匠村民頭顱","librarian":"雪原圖書管理員村民頭顱","mason":"雪原石匠村民頭顱","nitwit":"雪原傻子村民頭顱","none":"雪原村民頭顱","shepherd":"雪原牧羊人村民頭顱","toolsmith":"雪原工具匠村民頭顱","weaponsmith":"雪原武器匠村民頭顱"},"swamp":{"armorer":"沼澤盔甲匠村民頭顱","butcher":"沼澤屠夫村民頭顱","cartographer":"沼澤製圖師村民頭顱","cleric":"沼澤神職人員村民頭顱","farmer":"沼澤農夫村民頭顱","fisherman":"沼澤漁夫村民頭顱","fletcher":"沼澤製箭師村民頭顱","leatherworker":"沼澤皮匠村民頭顱","librarian":"沼澤圖書管理員村民頭顱","mason":"沼澤石匠村民頭顱","nitwit":"沼澤傻子村民頭顱","none":"沼澤村民頭顱","shepherd":"沼澤牧羊人村民頭顱","toolsmith":"沼澤工具匠村民頭顱","weaponsmith":"沼澤武器匠村民頭顱"},"taiga":{"armorer":"針葉林盔甲匠村民頭顱","butcher":"針葉林屠夫村民頭顱","cartographer":"針葉林製圖師村民頭顱","cleric":"針葉林神職人員村民頭顱","farmer":"針葉林農夫村民頭顱","fisherman":"針葉林漁夫村民頭顱","fletcher":"針葉林製箭師村民頭顱","leatherworker":"針葉林皮匠村民頭顱","librarian":"針葉林圖書管理員村民頭顱","mason":"針葉林石匠村民頭顱","nitwit":"針葉林傻子村民頭顱","none":"針葉林村民頭顱","shepherd":"針葉林牧羊人村民頭顱","toolsmith":"針葉林工具匠村民頭顱","weaponsmith":"針葉林武器匠村民頭顱"}},"vindicator":"衛道士頭顱","wandering_trader":"流浪商人頭顱","warden":"伏守者頭顱","witch":"巫婆頭顱","wither":{"normal":"凋零怪頭顱","projectile":"凋零怪投射物頭顱","blue_projectile":"藍色凋零怪投射物頭顱"},"wither_skeleton":"凋零骷髏頭顱","wolf":"狼頭顱","wolf_angry":"憤怒狼頭顱","zoglin":"豬屍獸頭顱","zombie":"殭屍頭顱","zombie_hoglin":"豬屍獸頭顱","zombie_horse":"殭屍馬頭顱","zombie_pigman":"殭屍豬人頭顱","zombified_piglin":"殭屍豬人頭顱","zombie_villager":{"armorer":"殭屍盔甲匠村民頭顱","butcher":"殭屍屠夫村民頭顱","cartographer":"殭屍製圖師村民頭顱","cleric":"殭屍神職人員村民頭顱","farmer":"殭屍農夫村民頭顱","fisherman":"殭屍漁夫村民頭顱","fletcher":"殭屍製箭師村民頭顱","leatherworker":"殭屍皮匠村民頭顱","librarian":"殭屍圖書管理員村民頭顱","mason":"殭屍石匠村民頭顱","nitwit":"殭屍傻子村民頭顱","none":"殭屍村民頭顱","shepherd":"殭屍牧羊人村民頭顱","toolsmith":"殭屍工具匠村民頭顱","weaponsmith":"殭屍武器匠村民頭顱"}}